{
  "openapi": "3.0.1",
  "info": {
    "title": "MultipleHtppClient.API",
    "version": "1.0"
  },
  "paths": {
    "/api/Presentation/All": {
      "get": {
        "tags": [
          "Presentation"
        ],
        "responses": {
          "200": {
            "description": "OK"
          }
        }
      }
    },
    "/api/Presentation/{id}": {
      "get": {
        "tags": [
          "Presentation"
        ],
        "parameters": [
          {
            "name": "id",
            "in": "path",
            "required": true,
            "schema": {
              "type": "integer",
              "format": "int32"
            }
          }
        ],
        "responses": {
          "200": {
            "description": "OK"
          }
        }
      }
    },
    "/api/Presentation/ticker": {
      "get": {
        "tags": [
          "Presentation"
        ],
        "responses": {
          "200": {
            "description": "OK"
          }
        }
      }
    },
    "/api/v2/utilisateur/Cantrylogin": {
      "post": {
        "tags": [
          "Presentation"
        ],
        "requestBody": {
          "content": {
            "application/json": {
              "schema": {
                "$ref": "#/components/schemas/CanTryLoginRequestBody"
              }
            },
            "text/json": {
              "schema": {
                "$ref": "#/components/schemas/CanTryLoginRequestBody"
              }
            },
            "application/*+json": {
              "schema": {
                "$ref": "#/components/schemas/CanTryLoginRequestBody"
              }
            }
          }
        },
        "responses": {
          "200": {
            "description": "OK",
            "content": {
              "text/plain": {
                "schema": {
                  "$ref": "#/components/schemas/AglouUserAglou10001Response"
                }
              },
              "application/json": {
                "schema": {
                  "$ref": "#/components/schemas/AglouUserAglou10001Response"
                }
              },
              "text/json": {
                "schema": {
                  "$ref": "#/components/schemas/AglouUserAglou10001Response"
                }
              }
            }
          }
        }
      }
    },
    "/api/v2/utilisateur/Login": {
      "post": {
        "tags": [
          "Presentation"
        ],
        "requestBody": {
          "content": {
            "application/json": {
              "schema": {
                "$ref": "#/components/schemas/LoginRequestBody"
              }
            },
            "text/json": {
              "schema": {
                "$ref": "#/components/schemas/LoginRequestBody"
              }
            },
            "application/*+json": {
              "schema": {
                "$ref": "#/components/schemas/LoginRequestBody"
              }
            }
          }
        },
        "responses": {
          "200": {
            "description": "OK"
          }
        }
      }
    },
    "/api/v2/dossier/getCounts": {
      "post": {
        "tags": [
          "Presentation"
        ],
        "requestBody": {
          "content": {
            "application/json": {
              "schema": {
                "$ref": "#/components/schemas/GetDossierCountRequestBody"
              }
            },
            "text/json": {
              "schema": {
                "$ref": "#/components/schemas/GetDossierCountRequestBody"
              }
            },
            "application/*+json": {
              "schema": {
                "$ref": "#/components/schemas/GetDossierCountRequestBody"
              }
            }
          }
        },
        "responses": {
          "200": {
            "description": "OK",
            "content": {
              "text/plain": {
                "schema": {
                  "$ref": "#/components/schemas/DossierCountsAglou10001Response"
                }
              },
              "application/json": {
                "schema": {
                  "$ref": "#/components/schemas/DossierCountsAglou10001Response"
                }
              },
              "text/json": {
                "schema": {
                  "$ref": "#/components/schemas/DossierCountsAglou10001Response"
                }
              }
            }
          }
        }
      }
    },
    "/api/v2/typepartenaire/GetAll": {
      "post": {
        "tags": [
          "Presentation"
        ],
        "responses": {
          "200": {
            "description": "OK",
            "content": {
              "text/plain": {
                "schema": {
                  "$ref": "#/components/schemas/PartnersTypeIEnumerableAglou10001Response"
                }
              },
              "application/json": {
                "schema": {
                  "$ref": "#/components/schemas/PartnersTypeIEnumerableAglou10001Response"
                }
              },
              "text/json": {
                "schema": {
                  "$ref": "#/components/schemas/PartnersTypeIEnumerableAglou10001Response"
                }
              }
            }
          }
        }
      }
    },
    "/api/v2/statutdossier/GetAll": {
      "post": {
        "tags": [
          "Presentation"
        ],
        "requestBody": {
          "content": {
            "application/json": {
              "schema": {
                "$ref": "#/components/schemas/ProfileRoleRequestBody"
              }
            },
            "text/json": {
              "schema": {
                "$ref": "#/components/schemas/ProfileRoleRequestBody"
              }
            },
            "application/*+json": {
              "schema": {
                "$ref": "#/components/schemas/ProfileRoleRequestBody"
              }
            }
          }
        },
        "responses": {
          "200": {
            "description": "OK",
            "content": {
              "text/plain": {
                "schema": {
                  "$ref": "#/components/schemas/DossierStatusIEnumerableAglou10001Response"
                }
              },
              "application/json": {
                "schema": {
                  "$ref": "#/components/schemas/DossierStatusIEnumerableAglou10001Response"
                }
              },
              "text/json": {
                "schema": {
                  "$ref": "#/components/schemas/DossierStatusIEnumerableAglou10001Response"
                }
              }
            }
          }
        }
      }
    },
    "/api/v2/typedemende/GetAll": {
      "post": {
        "tags": [
          "Presentation"
        ],
        "responses": {
          "200": {
            "description": "OK",
            "content": {
              "text/plain": {
                "schema": {
                  "$ref": "#/components/schemas/DemandTypeIEnumerableAglou10001Response"
                }
              },
              "application/json": {
                "schema": {
                  "$ref": "#/components/schemas/DemandTypeIEnumerableAglou10001Response"
                }
              },
              "text/json": {
                "schema": {
                  "$ref": "#/components/schemas/DemandTypeIEnumerableAglou10001Response"
                }
              }
            }
          }
        }
      }
    },
    "/api/v2/decoupagecommercial/GetAll": {
      "post": {
        "tags": [
          "Presentation"
        ],
        "responses": {
          "200": {
            "description": "OK",
            "content": {
              "text/plain": {
                "schema": {
                  "$ref": "#/components/schemas/CommercialCuttingIEnumerableAglou10001Response"
                }
              },
              "application/json": {
                "schema": {
                  "$ref": "#/components/schemas/CommercialCuttingIEnumerableAglou10001Response"
                }
              },
              "text/json": {
                "schema": {
                  "$ref": "#/components/schemas/CommercialCuttingIEnumerableAglou10001Response"
                }
              }
            }
          }
        }
      }
    },
    "/api/v2/dossier/GetAll": {
      "post": {
        "tags": [
          "Presentation"
        ],
        "requestBody": {
          "content": {
            "application/json": {
              "schema": {
                "$ref": "#/components/schemas/ProfileRoleRequestBody"
              }
            },
            "text/json": {
              "schema": {
                "$ref": "#/components/schemas/ProfileRoleRequestBody"
              }
            },
            "application/*+json": {
              "schema": {
                "$ref": "#/components/schemas/ProfileRoleRequestBody"
              }
            }
          }
        },
        "responses": {
          "200": {
            "description": "OK",
            "content": {
              "text/plain": {
                "schema": {
                  "$ref": "#/components/schemas/DossierAllIEnumerableAglou10001Response"
                }
              },
              "application/json": {
                "schema": {
                  "$ref": "#/components/schemas/DossierAllIEnumerableAglou10001Response"
                }
              },
              "text/json": {
                "schema": {
                  "$ref": "#/components/schemas/DossierAllIEnumerableAglou10001Response"
                }
              }
            }
          }
        }
      }
    },
    "/api/v2/partenaire/GetAll": {
      "post": {
        "tags": [
          "Presentation"
        ],
        "responses": {
          "200": {
            "description": "OK",
            "content": {
              "text/plain": {
                "schema": {
                  "$ref": "#/components/schemas/PartnerIEnumerableAglou10001Response"
                }
              },
              "application/json": {
                "schema": {
                  "$ref": "#/components/schemas/PartnerIEnumerableAglou10001Response"
                }
              },
              "text/json": {
                "schema": {
                  "$ref": "#/components/schemas/PartnerIEnumerableAglou10001Response"
                }
              }
            }
          }
        }
      }
    },
    "/api/v2/dossier/Search": {
      "post": {
        "tags": [
          "Presentation"
        ],
        "requestBody": {
          "content": {
            "application/json": {
              "schema": {
                "$ref": "#/components/schemas/SearchDossierRequestBody"
              }
            },
            "text/json": {
              "schema": {
                "$ref": "#/components/schemas/SearchDossierRequestBody"
              }
            },
            "application/*+json": {
              "schema": {
                "$ref": "#/components/schemas/SearchDossierRequestBody"
              }
            }
          }
        },
        "responses": {
          "200": {
            "description": "OK",
            "content": {
              "text/plain": {
                "schema": {
                  "$ref": "#/components/schemas/DossierSearchResponseIEnumerableAglou10001Response"
                }
              },
              "application/json": {
                "schema": {
                  "$ref": "#/components/schemas/DossierSearchResponseIEnumerableAglou10001Response"
                }
              },
              "text/json": {
                "schema": {
                  "$ref": "#/components/schemas/DossierSearchResponseIEnumerableAglou10001Response"
                }
              }
            }
          }
        }
      }
    },
    "/api/v2/utilisateur/Logout": {
      "post": {
        "tags": [
          "Presentation"
        ],
        "requestBody": {
          "content": {
            "application/json": {
              "schema": {
                "$ref": "#/components/schemas/LogoutRequestBody"
              }
            },
            "text/json": {
              "schema": {
                "$ref": "#/components/schemas/LogoutRequestBody"
              }
            },
            "application/*+json": {
              "schema": {
                "$ref": "#/components/schemas/LogoutRequestBody"
              }
            }
          }
        },
        "responses": {
          "200": {
            "description": "OK",
            "content": {
              "text/plain": {
                "schema": {
                  "$ref": "#/components/schemas/ObjectAglou10001Response"
                }
              },
              "application/json": {
                "schema": {
                  "$ref": "#/components/schemas/ObjectAglou10001Response"
                }
              },
              "text/json": {
                "schema": {
                  "$ref": "#/components/schemas/ObjectAglou10001Response"
                }
              }
            }
          }
        }
      }
    },
    "/api/v2/natureactivite/GetAll": {
      "post": {
        "tags": [
          "Presentation"
        ],
        "responses": {
          "200": {
            "description": "OK",
            "content": {
              "text/plain": {
                "schema": {
                  "$ref": "#/components/schemas/ActivityNatureResponseIEnumerableAglou10001Response"
                }
              },
              "application/json": {
                "schema": {
                  "$ref": "#/components/schemas/ActivityNatureResponseIEnumerableAglou10001Response"
                }
              },
              "text/json": {
                "schema": {
                  "$ref": "#/components/schemas/ActivityNatureResponseIEnumerableAglou10001Response"
                }
              }
            }
          }
        }
      }
    },
    "/api/v2/pack/GetAll": {
      "post": {
        "tags": [
          "Presentation"
        ],
        "responses": {
          "200": {
            "description": "OK",
            "content": {
              "text/plain": {
                "schema": {
                  "$ref": "#/components/schemas/PackResponseIEnumerableAglou10001Response"
                }
              },
              "application/json": {
                "schema": {
                  "$ref": "#/components/schemas/PackResponseIEnumerableAglou10001Response"
                }
              },
              "text/json": {
                "schema": {
                  "$ref": "#/components/schemas/PackResponseIEnumerableAglou10001Response"
                }
              }
            }
          }
        }
      }
    },
    "/api/v2/ville/GetAll": {
      "post": {
        "tags": [
          "Presentation"
        ],
        "responses": {
          "200": {
            "description": "OK",
            "content": {
              "text/plain": {
                "schema": {
                  "$ref": "#/components/schemas/VilleResponseIEnumerableAglou10001Response"
                }
              },
              "application/json": {
                "schema": {
                  "$ref": "#/components/schemas/VilleResponseIEnumerableAglou10001Response"
                }
              },
              "text/json": {
                "schema": {
                  "$ref": "#/components/schemas/VilleResponseIEnumerableAglou10001Response"
                }
              }
            }
          }
        }
      }
    },
    "/api/v2/arrondissement/GetAll": {
      "post": {
        "tags": [
          "Presentation"
        ],
        "responses": {
          "200": {
            "description": "OK",
            "content": {
              "text/plain": {
                "schema": {
                  "$ref": "#/components/schemas/ArrondissementResponseIEnumerableAglou10001Response"
                }
              },
              "application/json": {
                "schema": {
                  "$ref": "#/components/schemas/ArrondissementResponseIEnumerableAglou10001Response"
                }
              },
              "text/json": {
                "schema": {
                  "$ref": "#/components/schemas/ArrondissementResponseIEnumerableAglou10001Response"
                }
              }
            }
          }
        }
      }
    },
    "/api/v2/typebien/GetAll": {
      "post": {
        "tags": [
          "Presentation"
        ],
        "responses": {
          "200": {
            "description": "OK",
            "content": {
              "text/plain": {
                "schema": {
                  "$ref": "#/components/schemas/TypeBienResponseIEnumerableAglou10001Response"
                }
              },
              "application/json": {
                "schema": {
                  "$ref": "#/components/schemas/TypeBienResponseIEnumerableAglou10001Response"
                }
              },
              "text/json": {
                "schema": {
                  "$ref": "#/components/schemas/TypeBienResponseIEnumerableAglou10001Response"
                }
              }
            }
          }
        }
      }
    },
    "/api/v2/region/GetAll": {
      "post": {
        "tags": [
          "Presentation"
        ],
        "responses": {
          "200": {
            "description": "OK",
            "content": {
              "text/plain": {
                "schema": {
                  "$ref": "#/components/schemas/RegionResponseIEnumerableAglou10001Response"
                }
              },
              "application/json": {
                "schema": {
                  "$ref": "#/components/schemas/RegionResponseIEnumerableAglou10001Response"
                }
              },
              "text/json": {
                "schema": {
                  "$ref": "#/components/schemas/RegionResponseIEnumerableAglou10001Response"
                }
              }
            }
          }
        }
      }
    },
    "/api/v2/utilisateur/PasswordForgotten": {
      "post": {
        "tags": [
          "Presentation"
        ],
        "requestBody": {
          "content": {
            "application/json": {
              "schema": {
                "$ref": "#/components/schemas/ForgetPasswordRequestBody"
              }
            },
            "text/json": {
              "schema": {
                "$ref": "#/components/schemas/ForgetPasswordRequestBody"
              }
            },
            "application/*+json": {
              "schema": {
                "$ref": "#/components/schemas/ForgetPasswordRequestBody"
              }
            }
          }
        },
        "responses": {
          "200": {
            "description": "OK",
            "content": {
              "text/plain": {
                "schema": {
                  "$ref": "#/components/schemas/ObjectAglou10001Response"
                }
              },
              "application/json": {
                "schema": {
                  "$ref": "#/components/schemas/ObjectAglou10001Response"
                }
              },
              "text/json": {
                "schema": {
                  "$ref": "#/components/schemas/ObjectAglou10001Response"
                }
              }
            }
          }
        }
      }
    },
    "/api/v2/utilisateur/UpdatePassWord": {
      "post": {
        "tags": [
          "Presentation"
        ],
        "requestBody": {
          "content": {
            "application/json": {
              "schema": {
                "$ref": "#/components/schemas/UpdatePasswordRequestBody"
              }
            },
            "text/json": {
              "schema": {
                "$ref": "#/components/schemas/UpdatePasswordRequestBody"
              }
            },
            "application/*+json": {
              "schema": {
                "$ref": "#/components/schemas/UpdatePasswordRequestBody"
              }
            }
          }
        },
        "responses": {
          "200": {
            "description": "OK",
            "content": {
              "text/plain": {
                "schema": {
                  "$ref": "#/components/schemas/StringAglou10001Response"
                }
              },
              "application/json": {
                "schema": {
                  "$ref": "#/components/schemas/StringAglou10001Response"
                }
              },
              "text/json": {
                "schema": {
                  "$ref": "#/components/schemas/StringAglou10001Response"
                }
              }
            }
          }
        }
      }
    },
    "/api/v2/dossier/Load": {
      "post": {
        "tags": [
          "Presentation"
        ],
        "requestBody": {
          "content": {
            "application/json": {
              "schema": {
                "$ref": "#/components/schemas/LogoutRequestBody"
              }
            },
            "text/json": {
              "schema": {
                "$ref": "#/components/schemas/LogoutRequestBody"
              }
            },
            "application/*+json": {
              "schema": {
                "$ref": "#/components/schemas/LogoutRequestBody"
              }
            }
          }
        },
        "responses": {
          "200": {
            "description": "OK",
            "content": {
              "text/plain": {
                "schema": {
                  "$ref": "#/components/schemas/LoadDossierResponseAglou10001Response"
                }
              },
              "application/json": {
                "schema": {
                  "$ref": "#/components/schemas/LoadDossierResponseAglou10001Response"
                }
              },
              "text/json": {
                "schema": {
                  "$ref": "#/components/schemas/LoadDossierResponseAglou10001Response"
                }
              }
            }
          }
        }
      }
    },
    "/api/v2/historique/Search": {
      "post": {
        "tags": [
          "Presentation"
        ],
        "requestBody": {
          "content": {
            "application/json": {
              "schema": {
                "$ref": "#/components/schemas/HistorySearchRequestBody"
              }
            },
            "text/json": {
              "schema": {
                "$ref": "#/components/schemas/HistorySearchRequestBody"
              }
            },
            "application/*+json": {
              "schema": {
                "$ref": "#/components/schemas/HistorySearchRequestBody"
              }
            }
          }
        },
        "responses": {
          "200": {
            "description": "OK",
            "content": {
              "text/plain": {
                "schema": {
                  "$ref": "#/components/schemas/HistroySearchResponseAglou10001Response"
                }
              },
              "application/json": {
                "schema": {
                  "$ref": "#/components/schemas/HistroySearchResponseAglou10001Response"
                }
              },
              "text/json": {
                "schema": {
                  "$ref": "#/components/schemas/HistroySearchResponseAglou10001Response"
                }
              }
            }
          }
        }
      }
    },
    "/api/v2/dossier/Update": {
      "post": {
        "tags": [
          "Presentation"
        ],
        "requestBody": {
          "content": {
            "application/json": {
              "schema": {
                "$ref": "#/components/schemas/UpdateDossierRequestBody"
              }
            },
            "text/json": {
              "schema": {
                "$ref": "#/components/schemas/UpdateDossierRequestBody"
              }
            },
            "application/*+json": {
              "schema": {
                "$ref": "#/components/schemas/UpdateDossierRequestBody"
              }
            }
          }
        },
        "responses": {
          "200": {
            "description": "OK",
            "content": {
              "text/plain": {
                "schema": {
                  "$ref": "#/components/schemas/ObjectAglou10001Response"
                }
              },
              "application/json": {
                "schema": {
                  "$ref": "#/components/schemas/ObjectAglou10001Response"
                }
              },
              "text/json": {
                "schema": {
                  "$ref": "#/components/schemas/ObjectAglou10001Response"
                }
              }
            }
          }
        }
      }
    },
    "/api/v2/dossier/Insert": {
      "post": {
        "tags": [
          "Presentation"
        ],
        "requestBody": {
          "content": {
            "multipart/form-data": {
              "schema": {
                "type": "object",
                "properties": {
                  "id_statutdossier": {
                    "type": "string"
                  },
                  "user_id": {
                    "type": "string"
                  },
                  "id_typedemende": {
                    "type": "string"
                  },
                  "id_natureactivite": {
                    "type": "string"
                  },
                  "id_region": {
                    "type": "string"
                  },
                  "id_ville": {
                    "type": "string"
                  },
                  "id_arrandissement": {
                    "type": "string"
                  },
                  "adresslocal": {
                    "type": "string"
                  },
                  "id_visibilite": {
                    "type": "string"
                  },
                  "superficie": {
                    "type": "string"
                  },
                  "presence_sanitaire": {
                    "type": "string"
                  },
                  "id_typebien": {
                    "type": "string"
                  },
                  "prix": {
                    "type": "string"
                  },
                  "facade": {
                    "type": "string"
                  },
                  "Latitude": {
                    "type": "string"
                  },
                  "Longitude": {
                    "type": "string"
                  },
                  "horaire_ouverture": {
                    "type": "string"
                  },
                  "jour_ouverture": {
                    "type": "string"
                  },
                  "anne_experience": {
                    "type": "string"
                  },
                  "commentairelocal": {
                    "type": "string"
                  },
                  "ice": {
                    "type": "string"
                  },
                  "rc": {
                    "type": "string"
                  },
                  "autre_ville": {
                    "type": "string"
                  },
                  "nomlocal": {
                    "type": "string"
                  },
                  "nom_ag_WFC_proche": {
                    "type": "string"
                  },
                  "dist_bur_WFC_proche": {
                    "type": "string"
                  },
                  "dist_ag_WFC_proche": {
                    "type": "string"
                  },
                  "potentiel": {
                    "type": "string"
                  },
                  "pack": {
                    "type": "string"
                  },
                  "forme_juridique": {
                    "type": "string"
                  },
                  "regime_imposi": {
                    "type": "string"
                  },
                  "mode_mandataire": {
                    "type": "string"
                  },
                  "identification_fiscale": {
                    "type": "string"
                  },
                  "photosInterieur_0": {
                    "type": "string"
                  },
                  "photosExterieur_0": {
                    "type": "string"
                  }
                }
              },
              "encoding": {
                "id_statutdossier": {
                  "style": "form"
                },
                "user_id": {
                  "style": "form"
                },
                "id_typedemende": {
                  "style": "form"
                },
                "id_natureactivite": {
                  "style": "form"
                },
                "id_region": {
                  "style": "form"
                },
                "id_ville": {
                  "style": "form"
                },
                "id_arrandissement": {
                  "style": "form"
                },
                "adresslocal": {
                  "style": "form"
                },
                "id_visibilite": {
                  "style": "form"
                },
                "superficie": {
                  "style": "form"
                },
                "presence_sanitaire": {
                  "style": "form"
                },
                "id_typebien": {
                  "style": "form"
                },
                "prix": {
                  "style": "form"
                },
                "facade": {
                  "style": "form"
                },
                "Latitude": {
                  "style": "form"
                },
                "Longitude": {
                  "style": "form"
                },
                "horaire_ouverture": {
                  "style": "form"
                },
                "jour_ouverture": {
                  "style": "form"
                },
                "anne_experience": {
                  "style": "form"
                },
                "commentairelocal": {
                  "style": "form"
                },
                "ice": {
                  "style": "form"
                },
                "rc": {
                  "style": "form"
                },
                "autre_ville": {
                  "style": "form"
                },
                "nomlocal": {
                  "style": "form"
                },
                "nom_ag_WFC_proche": {
                  "style": "form"
                },
                "dist_bur_WFC_proche": {
                  "style": "form"
                },
                "dist_ag_WFC_proche": {
                  "style": "form"
                },
                "potentiel": {
                  "style": "form"
                },
                "pack": {
                  "style": "form"
                },
                "forme_juridique": {
                  "style": "form"
                },
                "regime_imposi": {
                  "style": "form"
                },
                "mode_mandataire": {
                  "style": "form"
                },
                "identification_fiscale": {
                  "style": "form"
                },
                "photosInterieur_0": {
                  "style": "form"
                },
                "photosExterieur_0": {
                  "style": "form"
                }
              }
            }
          }
        },
        "responses": {
          "200": {
            "description": "OK",
            "content": {
              "text/plain": {
                "schema": {
                  "$ref": "#/components/schemas/ObjectAglou10001Response"
                }
              },
              "application/json": {
                "schema": {
                  "$ref": "#/components/schemas/ObjectAglou10001Response"
                }
              },
              "text/json": {
                "schema": {
                  "$ref": "#/components/schemas/ObjectAglou10001Response"
                }
              }
            }
          }
        }
      }
    }
  },
  "components": {
    "schemas": {
      "ActivityNatureResponse": {
        "type": "object",
        "properties": {
          "id": {
            "type": "integer",
            "format": "int32"
          },
          "nature_activite": {
            "type": "string",
            "nullable": true
          },
          "name_activite": {
            "type": "string",
            "nullable": true
          }
        },
        "additionalProperties": false
      },
      "ActivityNatureResponseIEnumerableAglou10001Response": {
        "type": "object",
        "properties": {
          "codeReponse": {
            "type": "integer",
            "format": "int32"
          },
          "msg": {
            "type": "string",
            "nullable": true
          },
          "data": {
            "type": "array",
            "items": {
              "$ref": "#/components/schemas/ActivityNatureResponse"
            },
            "nullable": true
          },
          "NbRows": {
            "type": "integer",
            "format": "int32"
          },
          "TotalRows": {
            "type": "integer",
            "format": "int32"
          }
        },
        "additionalProperties": false
      },
      "AglouUser": {
        "type": "object",
        "properties": {
          "user_id": {
            "type": "string",
            "nullable": true
          },
          "nom": {
            "type": "string",
            "nullable": true
          },
          "prenom": {
            "type": "string",
            "nullable": true
          },
          "date_tent": {
            "type": "string",
            "format": "date-time"
          },
          "isactive": {
            "type": "boolean"
          },
          "tentativecount": {
            "type": "integer",
            "format": "int32"
          },
          "isupdatepassword": {
            "type": "boolean"
          },
          "password": {
            "type": "string",
            "nullable": true
          },
          "date_updatepassword": {
            "type": "string",
            "format": "date-time"
          }
        },
        "additionalProperties": false
      },
      "AglouUserAglou10001Response": {
        "type": "object",
        "properties": {
          "codeReponse": {
            "type": "integer",
            "format": "int32"
          },
          "msg": {
            "type": "string",
            "nullable": true
          },
          "data": {
            "$ref": "#/components/schemas/AglouUser"
          },
          "NbRows": {
            "type": "integer",
            "format": "int32"
          },
          "TotalRows": {
            "type": "integer",
            "format": "int32"
          }
        },
        "additionalProperties": false
      },
      "ArrondissementResponse": {
        "type": "object",
        "properties": {
          "id": {
            "type": "integer",
            "format": "int32"
          },
          "label": {
            "type": "string",
            "nullable": true
          }
        },
        "additionalProperties": false
      },
      "ArrondissementResponseIEnumerableAglou10001Response": {
        "type": "object",
        "properties": {
          "codeReponse": {
            "type": "integer",
            "format": "int32"
          },
          "msg": {
            "type": "string",
            "nullable": true
          },
          "data": {
            "type": "array",
            "items": {
              "$ref": "#/components/schemas/ArrondissementResponse"
            },
            "nullable": true
          },
          "NbRows": {
            "type": "integer",
            "format": "int32"
          },
          "TotalRows": {
            "type": "integer",
            "format": "int32"
          }
        },
        "additionalProperties": false
      },
      "CanTryLoginRequestBody": {
        "type": "object",
        "properties": {
          "email": {
            "type": "string",
            "nullable": true
          }
        },
        "additionalProperties": false
      },
      "Commentaire": {
        "type": "object",
        "properties": {
          "id": {
            "type": "integer",
            "format": "int32"
          },
          "id_dossier": {
            "type": "integer",
            "format": "int32",
            "nullable": true
          },
          "commentaire": {
            "type": "string",
            "nullable": true
          },
          "date_created": {
            "type": "string",
            "format": "date-time",
            "nullable": true
          },
          "date_updated": {
            "type": "string",
            "format": "date-time",
            "nullable": true
          },
          "date_deleted": {
            "type": "string",
            "format": "date-time",
            "nullable": true
          },
          "user_created": {
            "type": "integer",
            "format": "int32",
            "nullable": true
          },
          "user_updated": {
            "type": "integer",
            "format": "int32",
            "nullable": true
          },
          "user_deleted": {
            "type": "integer",
            "format": "int32",
            "nullable": true
          },
          "id_dossierNavigation": {
            "type": "string",
            "nullable": true
          }
        },
        "additionalProperties": false
      },
      "CommercialCutting": {
        "type": "object",
        "properties": {
          "id": {
            "type": "integer",
            "format": "int32"
          },
          "label": {
            "type": "string",
            "nullable": true
          }
        },
        "additionalProperties": false
      },
      "CommercialCuttingIEnumerableAglou10001Response": {
        "type": "object",
        "properties": {
          "codeReponse": {
            "type": "integer",
            "format": "int32"
          },
          "msg": {
            "type": "string",
            "nullable": true
          },
          "data": {
            "type": "array",
            "items": {
              "$ref": "#/components/schemas/CommercialCutting"
            },
            "nullable": true
          },
          "NbRows": {
            "type": "integer",
            "format": "int32"
          },
          "TotalRows": {
            "type": "integer",
            "format": "int32"
          }
        },
        "additionalProperties": false
      },
      "DebugInfo": {
        "type": "object",
        "properties": {
          "ProfileId": {
            "type": "integer",
            "format": "int32"
          },
          "UserId": {
            "type": "integer",
            "format": "int32"
          },
          "DecoupageCommercialId": {
            "type": "string",
            "nullable": true
          },
          "AppliqueFilter": {
            "type": "boolean"
          },
          "ConfiguredStatuses": {
            "type": "array",
            "items": {
              "type": "integer",
              "format": "int32"
            },
            "nullable": true
          },
          "CurrentStatusDistribution": {
            "type": "array",
            "items": { },
            "nullable": true
          },
          "FinalCounts": {
            "$ref": "#/components/schemas/FinalCounts"
          }
        },
        "additionalProperties": false
      },
      "DemandType": {
        "type": "object",
        "properties": {
          "id": {
            "type": "integer",
            "format": "int32"
          },
          "label": {
            "type": "string",
            "nullable": true
          },
          "description": {
            "type": "string",
            "nullable": true
          }
        },
        "additionalProperties": false
      },
      "DemandTypeIEnumerableAglou10001Response": {
        "type": "object",
        "properties": {
          "codeReponse": {
            "type": "integer",
            "format": "int32"
          },
          "msg": {
            "type": "string",
            "nullable": true
          },
          "data": {
            "type": "array",
            "items": {
              "$ref": "#/components/schemas/DemandType"
            },
            "nullable": true
          },
          "NbRows": {
            "type": "integer",
            "format": "int32"
          },
          "TotalRows": {
            "type": "integer",
            "format": "int32"
          }
        },
        "additionalProperties": false
      },
      "DossierAll": {
        "type": "object",
        "properties": {
          "id": {
            "type": "integer",
            "format": "int32"
          },
          "Code": {
            "type": "string",
            "nullable": true
          },
          "id_typedemende": {
            "type": "integer",
            "format": "int32"
          },
          "id_statutdossier": {
            "type": "integer",
            "format": "int32"
          },
          "statut": {
            "type": "string",
            "nullable": true
          }
        },
        "additionalProperties": false
      },
      "DossierAllIEnumerableAglou10001Response": {
        "type": "object",
        "properties": {
          "codeReponse": {
            "type": "integer",
            "format": "int32"
          },
          "msg": {
            "type": "string",
            "nullable": true
          },
          "data": {
            "type": "array",
            "items": {
              "$ref": "#/components/schemas/DossierAll"
            },
            "nullable": true
          },
          "NbRows": {
            "type": "integer",
            "format": "int32"
          },
          "TotalRows": {
            "type": "integer",
            "format": "int32"
          }
        },
        "additionalProperties": false
      },
      "DossierCounts": {
        "type": "object",
        "properties": {
          "TotalDossier": {
            "type": "integer",
            "format": "int32"
          },
          "TotalDossierTraiter": {
            "type": "integer",
            "format": "int32"
          },
          "TotalDossierEncours": {
            "type": "integer",
            "format": "int32"
          },
          "DebugInfo": {
            "$ref": "#/components/schemas/DebugInfo"
          }
        },
        "additionalProperties": false
      },
      "DossierCountsAglou10001Response": {
        "type": "object",
        "properties": {
          "codeReponse": {
            "type": "integer",
            "format": "int32"
          },
          "msg": {
            "type": "string",
            "nullable": true
          },
          "data": {
            "$ref": "#/components/schemas/DossierCounts"
          },
          "NbRows": {
            "type": "integer",
            "format": "int32"
          },
          "TotalRows": {
            "type": "integer",
            "format": "int32"
          }
        },
        "additionalProperties": false
      },
      "DossierSearchResponse": {
        "type": "object",
        "properties": {
          "id": {
            "type": "integer",
            "format": "int32"
          },
          "Code": {
            "type": "string",
            "nullable": true
          },
          "id_natureactivite": {
            "type": "integer",
            "format": "int32",
            "nullable": true
          },
          "id_typedemende": {
            "type": "integer",
            "format": "int32"
          },
          "id_decoupagecommercial": {
            "type": "integer",
            "format": "int32"
          },
          "decopagecmr": {
            "type": "string",
            "nullable": true
          },
          "id_statutdossier": {
            "type": "integer",
            "format": "int32"
          },
          "canupdate": {
            "type": "boolean"
          },
          "typedemende": {
            "type": "string",
            "nullable": true
          },
          "natureactivite": {
            "type": "string",
            "nullable": true
          },
          "partenaire": {
            "type": "string",
            "nullable": true
          },
          "LocalDossier": {
            "$ref": "#/components/schemas/LocalDossier"
          },
          "statut": {
            "type": "string",
            "nullable": true
          },
          "labelstatut": {
            "type": "string",
            "nullable": true
          },
          "date_created": {
            "type": "string",
            "nullable": true
          }
        },
        "additionalProperties": false
      },
      "DossierSearchResponseIEnumerableAglou10001Response": {
        "type": "object",
        "properties": {
          "codeReponse": {
            "type": "integer",
            "format": "int32"
          },
          "msg": {
            "type": "string",
            "nullable": true
          },
          "data": {
            "type": "array",
            "items": {
              "$ref": "#/components/schemas/DossierSearchResponse"
            },
            "nullable": true
          },
          "NbRows": {
            "type": "integer",
            "format": "int32"
          },
          "TotalRows": {
            "type": "integer",
            "format": "int32"
          }
        },
        "additionalProperties": false
      },
      "DossierStatus": {
        "type": "object",
        "properties": {
          "id": {
            "type": "integer",
            "format": "int32"
          },
          "label": {
            "type": "string",
            "nullable": true
          },
          "statut": {
            "type": "string",
            "nullable": true
          },
          "code": {
            "type": "string",
            "nullable": true
          },
          "color": {
            "type": "string",
            "nullable": true
          },
          "canupdate": {
            "type": "boolean"
          },
          "canuploade": {
            "type": "boolean"
          },
          "havemail": {
            "type": "boolean"
          },
          "mailname": {
            "type": "string",
            "nullable": true
          },
          "mailSubject": {
            "type": "string",
            "nullable": true
          },
          "action": {
            "type": "string",
            "nullable": true
          },
          "statuscode": {
            "type": "string",
            "nullable": true
          }
        },
        "additionalProperties": false
      },
      "DossierStatusIEnumerableAglou10001Response": {
        "type": "object",
        "properties": {
          "codeReponse": {
            "type": "integer",
            "format": "int32"
          },
          "msg": {
            "type": "string",
            "nullable": true
          },
          "data": {
            "type": "array",
            "items": {
              "$ref": "#/components/schemas/DossierStatus"
            },
            "nullable": true
          },
          "NbRows": {
            "type": "integer",
            "format": "int32"
          },
          "TotalRows": {
            "type": "integer",
            "format": "int32"
          }
        },
        "additionalProperties": false
      },
      "FinalCounts": {
        "type": "object",
        "properties": {
          "Total": {
            "type": "integer",
            "format": "int32"
          },
          "Treated": {
            "type": "integer",
            "format": "int32"
          },
          "Pending": {
            "type": "integer",
            "format": "int32"
          }
        },
        "additionalProperties": false
      },
      "ForgetPasswordRequestBody": {
        "type": "object",
        "properties": {
          "mail": {
            "type": "string",
            "nullable": true
          }
        },
        "additionalProperties": false
      },
      "GetDossierCountRequestBody": {
        "type": "object",
        "properties": {
          "userId": {
            "type": "string",
            "nullable": true
          },
          "idRole": {
            "type": "string",
            "nullable": true
          },
          "applyFilter": {
            "type": "boolean"
          }
        },
        "additionalProperties": false
      },
      "HistoryItem": {
        "type": "object",
        "properties": {
          "date_created": {
            "type": "string",
            "format": "date-time",
            "nullable": true
          },
          "id_dossier": {
            "type": "integer",
            "format": "int32",
            "nullable": true
          },
          "id_statutprecedent": {
            "type": "integer",
            "format": "int32",
            "nullable": true
          },
          "id_statutsuivant": {
            "type": "integer",
            "format": "int32",
            "nullable": true
          },
          "statutprecedent": {
            "type": "string",
            "nullable": true
          },
          "statutsuivant": {
            "type": "string",
            "nullable": true
          },
          "statutprecedentin": {
            "type": "string",
            "nullable": true
          },
          "statutsuivantin": {
            "type": "string",
            "nullable": true
          },
          "opperateur": {
            "type": "string",
            "nullable": true
          }
        },
        "additionalProperties": false
      },
      "HistorySearchRequestBody": {
        "type": "object",
        "properties": {
          "field": {
            "type": "string",
            "nullable": true
          },
          "id_dossier": {
            "type": "integer",
            "format": "int32"
          },
          "order": {
            "type": "string",
            "nullable": true
          },
          "skip": {
            "type": "integer",
            "format": "int32"
          },
          "take": {
            "type": "integer",
            "format": "int32"
          }
        },
        "additionalProperties": false
      },
      "HistroySearchResponse": {
        "type": "object",
        "properties": {
          "id": {
            "type": "integer",
            "format": "int32"
          },
          "date_created": {
            "type": "string",
            "nullable": true
          },
          "id_statutprecedent": {
            "type": "integer",
            "format": "int32"
          },
          "id_statutsuivant": {
            "type": "integer",
            "format": "int32"
          },
          "id_dossier": {
            "type": "integer",
            "format": "int32"
          },
          "dossier": {
            "type": "string",
            "nullable": true
          },
          "statutprecedent": {
            "type": "string",
            "nullable": true
          },
          "statutsuivant": {
            "type": "string",
            "nullable": true
          },
          "statutprecedentin": {
            "type": "string",
            "nullable": true
          },
          "statutsuivantin": {
            "type": "string",
            "nullable": true
          },
          "opperateur": {
            "type": "string",
            "nullable": true
          }
        },
        "additionalProperties": false
      },
      "HistroySearchResponseAglou10001Response": {
        "type": "object",
        "properties": {
          "codeReponse": {
            "type": "integer",
            "format": "int32"
          },
          "msg": {
            "type": "string",
            "nullable": true
          },
          "data": {
            "$ref": "#/components/schemas/HistroySearchResponse"
          },
          "NbRows": {
            "type": "integer",
            "format": "int32"
          },
          "TotalRows": {
            "type": "integer",
            "format": "int32"
          }
        },
        "additionalProperties": false
      },
      "LoadDossierResponse": {
        "type": "object",
        "properties": {
          "id": {
            "type": "integer",
            "format": "int32"
          },
          "id_natureactivite": {
            "type": "integer",
            "format": "int32",
            "nullable": true
          },
          "id_typedemende": {
            "type": "integer",
            "format": "int32",
            "nullable": true
          },
          "Code": {
            "type": "string",
            "nullable": true
          },
          "id_Partenaire": {
            "type": "integer",
            "format": "int32",
            "nullable": true
          },
          "id_statutdossier": {
            "type": "integer",
            "format": "int32",
            "nullable": true
          },
          "Commentaire": {
            "type": "array",
            "items": {
              "$ref": "#/components/schemas/Commentaire"
            },
            "nullable": true
          },
          "natureactivite": {
            "nullable": true
          },
          "nameactivite": {
            "nullable": true
          },
          "typedemende": {
            "type": "string",
            "nullable": true
          },
          "codestatut": {
            "type": "string",
            "nullable": true
          },
          "labelstatut": {
            "type": "string",
            "nullable": true
          },
          "statut": {
            "type": "string",
            "nullable": true
          },
          "canupload": {
            "type": "boolean"
          },
          "LocalDossier": {
            "$ref": "#/components/schemas/LocalDossierData"
          },
          "Partenaire": {
            "$ref": "#/components/schemas/Partner"
          },
          "Historique": {
            "type": "array",
            "items": {
              "$ref": "#/components/schemas/HistoryItem"
            },
            "nullable": true
          }
        },
        "additionalProperties": false
      },
      "LoadDossierResponseAglou10001Response": {
        "type": "object",
        "properties": {
          "codeReponse": {
            "type": "integer",
            "format": "int32"
          },
          "msg": {
            "type": "string",
            "nullable": true
          },
          "data": {
            "$ref": "#/components/schemas/LoadDossierResponse"
          },
          "NbRows": {
            "type": "integer",
            "format": "int32"
          },
          "TotalRows": {
            "type": "integer",
            "format": "int32"
          }
        },
        "additionalProperties": false
      },
      "LocalDossier": {
        "type": "object",
        "properties": {
          "id_dossier": {
            "type": "integer",
            "format": "int32"
          },
          "id": {
            "type": "integer",
            "format": "int32"
          },
          "Latitude": {
            "type": "string",
            "nullable": true
          },
          "Longitude": {
            "type": "string",
            "nullable": true
          },
          "adress": {
            "type": "string",
            "nullable": true
          },
          "zon": {
            "type": "string",
            "nullable": true
          },
          "ville": {
            "type": "string",
            "nullable": true
          },
          "decopagecmr": {
            "type": "string",
            "nullable": true
          },
          "region": {
            "type": "string",
            "nullable": true
          }
        },
        "additionalProperties": false
      },
      "LocalDossierData": {
        "type": "object",
        "properties": {
          "id_dossier": {
            "type": "integer",
            "format": "int32",
            "nullable": true
          },
          "id": {
            "type": "integer",
            "format": "int32"
          },
          "photosInterieur": {
            "nullable": true
          },
          "photosExterieur": {
            "nullable": true
          },
          "Latitude": {
            "type": "string",
            "nullable": true
          },
          "Longitude": {
            "type": "string",
            "nullable": true
          },
          "adress": {
            "type": "string",
            "nullable": true
          },
          "id_ville": {
            "type": "integer",
            "format": "int32",
            "nullable": true
          },
          "id_arrandissement": {
            "type": "integer",
            "format": "int32",
            "nullable": true
          },
          "commentaireLocal": {
            "type": "string",
            "nullable": true
          },
          "id_typebien": {
            "type": "integer",
            "format": "int32",
            "nullable": true
          },
          "adresslocal": {
            "type": "string",
            "nullable": true
          },
          "horaire_ouverture": {
            "type": "string",
            "nullable": true
          },
          "jour_ouverture": {
            "type": "string",
            "nullable": true
          },
          "id_visibilite": {
            "type": "integer",
            "format": "int32",
            "nullable": true
          },
          "superficie": {
            "type": "string",
            "nullable": true
          },
          "presence_sanitaire": {
            "type": "integer",
            "format": "int32",
            "nullable": true
          },
          "typebien": {
            "type": "string",
            "nullable": true
          },
          "facade": {
            "type": "string",
            "nullable": true
          },
          "anne_experience": {
            "type": "string",
            "nullable": true
          },
          "prix": {
            "type": "number",
            "format": "double",
            "nullable": true
          },
          "zon": {
            "type": "string",
            "nullable": true
          },
          "ville": {
            "type": "string",
            "nullable": true
          },
          "region": {
            "type": "string",
            "nullable": true
          },
          "arrondissement": {
            "type": "string",
            "nullable": true
          },
          "typelocalite": {
            "type": "string",
            "nullable": true
          },
          "decopagecmr": {
            "type": "string",
            "nullable": true
          },
          "nom_ag_WFC_proche": {
            "type": "string",
            "nullable": true
          },
          "dist_bur_WFC_proche": {
            "type": "string",
            "nullable": true
          },
          "potentiel": {
            "type": "integer",
            "format": "int32",
            "nullable": true
          },
          "dist_ag_WFC_proche": {
            "type": "string",
            "nullable": true
          },
          "pack": {
            "type": "string",
            "nullable": true
          },
          "id_pack": {
            "type": "integer",
            "format": "int32",
            "nullable": true
          },
          "nom": {
            "type": "string",
            "nullable": true
          }
        },
        "additionalProperties": false
      },
      "LoginRequestBody": {
        "type": "object",
        "properties": {
          "email": {
            "type": "string",
            "nullable": true
          },
          "password": {
            "type": "string",
            "nullable": true
          },
          "isotp": {
            "type": "boolean"
          }
        },
        "additionalProperties": false
      },
      "LogoutRequestBody": {
        "type": "object",
        "properties": {
          "id": {
            "type": "string",
            "nullable": true
          }
        },
        "additionalProperties": false
      },
      "ObjectAglou10001Response": {
        "type": "object",
        "properties": {
          "codeReponse": {
            "type": "integer",
            "format": "int32"
          },
          "msg": {
            "type": "string",
            "nullable": true
          },
          "data": {
            "nullable": true
          },
          "NbRows": {
            "type": "integer",
            "format": "int32"
          },
          "TotalRows": {
            "type": "integer",
            "format": "int32"
          }
        },
        "additionalProperties": false
      },
      "PackResponse": {
        "type": "object",
        "properties": {
          "id": {
            "type": "integer",
            "format": "int32"
          },
          "label": {
            "type": "string",
            "nullable": true
          },
          "arblabel": {
            "type": "string",
            "nullable": true
          },
          "description": {
            "type": "string",
            "nullable": true
          }
        },
        "additionalProperties": false
      },
      "PackResponseIEnumerableAglou10001Response": {
        "type": "object",
        "properties": {
          "codeReponse": {
            "type": "integer",
            "format": "int32"
          },
          "msg": {
            "type": "string",
            "nullable": true
          },
          "data": {
            "type": "array",
            "items": {
              "$ref": "#/components/schemas/PackResponse"
            },
            "nullable": true
          },
          "NbRows": {
            "type": "integer",
            "format": "int32"
          },
          "TotalRows": {
            "type": "integer",
            "format": "int32"
          }
        },
        "additionalProperties": false
      },
      "Partner": {
        "type": "object",
        "properties": {
          "id": {
            "type": "integer",
            "format": "int32"
          },
          "id_typepartenaire": {
            "type": "integer",
            "format": "int32",
            "nullable": true
          },
          "id_typepersonne": {
            "type": "integer",
            "format": "int32",
            "nullable": true
          },
          "id_ville": {
            "type": "integer",
            "format": "int32",
            "nullable": true
          },
          "id_region": {
            "type": "integer",
            "format": "int32",
            "nullable": true
          },
          "Code": {
            "type": "string",
            "nullable": true
          },
          "nom": {
            "type": "string",
            "nullable": true
          },
          "prenom": {
            "type": "string",
            "nullable": true
          },
          "mail": {
            "type": "string",
            "nullable": true
          },
          "telephone": {
            "type": "string",
            "nullable": true
          },
          "cin": {
            "type": "string",
            "nullable": true
          },
          "raison_sociale": {
            "type": "string",
            "nullable": true
          },
          "pid": {
            "type": "string",
            "nullable": true
          },
          "ice": {
            "type": "string",
            "nullable": true
          },
          "rc": {
            "type": "string",
            "nullable": true
          },
          "rib": {
            "type": "string",
            "nullable": true
          },
          "tp": {
            "type": "string",
            "nullable": true
          },
          "identification_fiscale": {
            "type": "string",
            "nullable": true
          },
          "forme_juridique": {
            "type": "integer",
            "format": "int32"
          },
          "regime_imposi": {
            "type": "integer",
            "format": "int32"
          },
          "mode_mandataire": {
            "type": "integer",
            "format": "int32"
          },
          "genre": {
            "type": "boolean"
          },
          "statut": {
            "type": "string",
            "nullable": true
          },
          "date_created": {
            "type": "string",
            "format": "date-time"
          },
          "date_updated": {
            "type": "string",
            "format": "date-time",
            "nullable": true
          },
          "date_deleted": {
            "type": "string",
            "format": "date-time",
            "nullable": true
          },
          "user_created": {
            "type": "integer",
            "format": "int32"
          },
          "user_updated": {
            "type": "integer",
            "format": "int32",
            "nullable": true
          },
          "user_deleted": {
            "type": "integer",
            "format": "int32",
            "nullable": true
          },
          "Dossier": {
            "type": "array",
            "items": { },
            "nullable": true
          },
          "id_villeNavigation": {
            "type": "string",
            "nullable": true
          },
          "id_regionNavigation": {
            "type": "string",
            "nullable": true
          },
          "id_typepartenaireNavigation": {
            "type": "string",
            "nullable": true
          },
          "id_typepersonneNavigation": {
            "type": "string",
            "nullable": true
          }
        },
        "additionalProperties": false
      },
      "PartnerIEnumerableAglou10001Response": {
        "type": "object",
        "properties": {
          "codeReponse": {
            "type": "integer",
            "format": "int32"
          },
          "msg": {
            "type": "string",
            "nullable": true
          },
          "data": {
            "type": "array",
            "items": {
              "$ref": "#/components/schemas/Partner"
            },
            "nullable": true
          },
          "NbRows": {
            "type": "integer",
            "format": "int32"
          },
          "TotalRows": {
            "type": "integer",
            "format": "int32"
          }
        },
        "additionalProperties": false
      },
      "PartnersType": {
        "type": "object",
        "properties": {
          "id": {
            "type": "integer",
            "format": "int32"
          },
          "label": {
            "type": "string",
            "nullable": true
          },
          "description": {
            "type": "string",
            "nullable": true
          }
        },
        "additionalProperties": false
      },
      "PartnersTypeIEnumerableAglou10001Response": {
        "type": "object",
        "properties": {
          "codeReponse": {
            "type": "integer",
            "format": "int32"
          },
          "msg": {
            "type": "string",
            "nullable": true
          },
          "data": {
            "type": "array",
            "items": {
              "$ref": "#/components/schemas/PartnersType"
            },
            "nullable": true
          },
          "NbRows": {
            "type": "integer",
            "format": "int32"
          },
          "TotalRows": {
            "type": "integer",
            "format": "int32"
          }
        },
        "additionalProperties": false
      },
      "ProfileRoleRequestBody": {
        "type": "object",
        "properties": {
          "id_role": {
            "type": "string",
            "nullable": true
          }
        },
        "additionalProperties": false
      },
      "RegionResponse": {
        "type": "object",
        "properties": {
          "id": {
            "type": "integer",
            "format": "int32",
            "nullable": true
          },
          "label": {
            "type": "string",
            "nullable": true
          },
          "logo": {
            "type": "string",
            "nullable": true
          },
          "map": {
            "type": "string",
            "nullable": true
          }
        },
        "additionalProperties": false
      },
      "RegionResponseIEnumerableAglou10001Response": {
        "type": "object",
        "properties": {
          "codeReponse": {
            "type": "integer",
            "format": "int32"
          },
          "msg": {
            "type": "string",
            "nullable": true
          },
          "data": {
            "type": "array",
            "items": {
              "$ref": "#/components/schemas/RegionResponse"
            },
            "nullable": true
          },
          "NbRows": {
            "type": "integer",
            "format": "int32"
          },
          "TotalRows": {
            "type": "integer",
            "format": "int32"
          }
        },
        "additionalProperties": false
      },
      "SearchDossierRequestBody": {
        "type": "object",
        "properties": {
          "user_id": {
            "type": "string",
            "nullable": true
          },
          "id_role": {
            "type": "string",
            "nullable": true
          },
          "appliquefilter": {
            "type": "boolean"
          },
          "Code": {
            "type": "string",
            "nullable": true
          },
          "id_statutdossier": {
            "type": "string",
            "nullable": true
          },
          "id_typedemende": {
            "type": "string",
            "nullable": true
          },
          "id_natureactivite": {
            "type": "string",
            "nullable": true
          },
          "id_partenaire": {
            "type": "string",
            "nullable": true
          },
          "id_decoupagecommercial": {
            "type": "string",
            "nullable": true
          },
          "datedebut": {
            "type": "string",
            "nullable": true
          },
          "datefin": {
            "type": "string",
            "nullable": true
          },
          "take": {
            "type": "integer",
            "format": "int32"
          },
          "skip": {
            "type": "integer",
            "format": "int32"
          },
          "field": {
            "type": "string",
            "nullable": true
          },
          "order": {
            "type": "string",
            "nullable": true
          }
        },
        "additionalProperties": false
      },
      "StringAglou10001Response": {
        "type": "object",
        "properties": {
          "codeReponse": {
            "type": "integer",
            "format": "int32"
          },
          "msg": {
            "type": "string",
            "nullable": true
          },
          "data": {
            "type": "string",
            "nullable": true
          },
          "NbRows": {
            "type": "integer",
            "format": "int32"
          },
          "TotalRows": {
            "type": "integer",
            "format": "int32"
          }
        },
        "additionalProperties": false
      },
      "TypeBienResponse": {
        "type": "object",
        "properties": {
          "id": {
            "type": "integer",
            "format": "int32"
          },
          "label": {
            "type": "string",
            "nullable": true
          }
        },
        "additionalProperties": false
      },
      "TypeBienResponseIEnumerableAglou10001Response": {
        "type": "object",
        "properties": {
          "codeReponse": {
            "type": "integer",
            "format": "int32"
          },
          "msg": {
            "type": "string",
            "nullable": true
          },
          "data": {
            "type": "array",
            "items": {
              "$ref": "#/components/schemas/TypeBienResponse"
            },
            "nullable": true
          },
          "NbRows": {
            "type": "integer",
            "format": "int32"
          },
          "TotalRows": {
            "type": "integer",
            "format": "int32"
          }
        },
        "additionalProperties": false
      },
      "UpdateDossierRequestBody": {
        "type": "object",
        "properties": {
          "user_id": {
            "type": "string",
            "nullable": true
          },
          "id_statutdossier": {
            "type": "integer",
            "format": "int32"
          },
          "id": {
            "type": "integer",
            "format": "int32"
          },
          "localid": {
            "type": "integer",
            "format": "int32"
          },
          "id_typedemende": {
            "type": "integer",
            "format": "int32"
          },
          "id_partenaire": {
            "type": "integer",
            "format": "int32"
          },
          "id_natureactivite": {
            "type": "integer",
            "format": "int32"
          },
          "id_ville": {
            "type": "integer",
            "format": "int32"
          },
          "id_arrandissement": {
            "type": "integer",
            "format": "int32"
          },
          "adresslocal": {
            "type": "string",
            "nullable": true
          },
          "id_visibilite": {
            "type": "integer",
            "format": "int32"
          },
          "superficie": {
            "type": "string",
            "nullable": true
          },
          "presence_sanitaire": {
            "type": "integer",
            "format": "int32"
          },
          "id_typebien": {
            "type": "integer",
            "format": "int32"
          },
          "prix": {
            "type": "number",
            "format": "double"
          },
          "facade": {
            "type": "string",
            "nullable": true
          },
          "Latitude": {
            "type": "string",
            "nullable": true
          },
          "Longitude": {
            "type": "string",
            "nullable": true
          },
          "horaire_ouverture": {
            "type": "string",
            "nullable": true
          },
          "jour_ouverture": {
            "type": "string",
            "nullable": true
          },
          "anne_experience": {
            "type": "string",
            "nullable": true
          },
          "commentairelocal": {
            "type": "string",
            "nullable": true
          },
          "ice": {
            "type": "string",
            "nullable": true
          },
          "rc": {
            "type": "string",
            "nullable": true
          },
          "autre_ville": {
            "type": "string",
            "nullable": true
          },
          "nomlocal": {
            "type": "string",
            "nullable": true
          },
          "nom_ag_WFC_proche": {
            "type": "string",
            "nullable": true
          },
          "dist_bur_WFC_proche": {
            "type": "string",
            "nullable": true
          },
          "dist_ag_WFC_proche": {
            "type": "string",
            "nullable": true
          },
          "potentiel": {
            "type": "integer",
            "format": "int32"
          },
          "pack": {
            "type": "integer",
            "format": "int32"
          },
          "forme_juridique": {
            "type": "integer",
            "format": "int32"
          },
          "regime_imposi": {
            "type": "integer",
            "format": "int32"
          },
          "mode_mandataire": {
            "type": "integer",
            "format": "int32"
          },
          "identification_fiscale": {
            "type": "string",
            "nullable": true
          }
        },
        "additionalProperties": false
      },
      "UpdatePasswordRequestBody": {
        "type": "object",
        "properties": {
          "id": {
            "type": "integer",
            "format": "int32"
          },
          "newPassword": {
            "type": "string",
            "nullable": true
          }
        },
        "additionalProperties": false
      },
      "VilleResponse": {
        "type": "object",
        "properties": {
          "id": {
            "type": "integer",
            "format": "int32"
          },
          "label": {
            "type": "string",
            "nullable": true
          },
          "id_region": {
            "type": "integer",
            "format": "int32",
            "nullable": true
          },
          "id_decoupagecommercial": {
            "type": "integer",
            "format": "int32",
            "nullable": true
          },
          "type_localite": {
            "type": "string",
            "nullable": true
          },
          "logo": {
            "type": "string",
            "nullable": true
          }
        },
        "additionalProperties": false
      },
      "VilleResponseIEnumerableAglou10001Response": {
        "type": "object",
        "properties": {
          "codeReponse": {
            "type": "integer",
            "format": "int32"
          },
          "msg": {
            "type": "string",
            "nullable": true
          },
          "data": {
            "type": "array",
            "items": {
              "$ref": "#/components/schemas/VilleResponse"
            },
            "nullable": true
          },
          "NbRows": {
            "type": "integer",
            "format": "int32"
          },
          "TotalRows": {
            "type": "integer",
            "format": "int32"
          }
        },
        "additionalProperties": false
      }
    }
  }
}